MANIFEST.in
requirements.txt
setup.py
cloudenvy/__init__.py
cloudenvy/config.py
cloudenvy/core.py
cloudenvy/exceptions.py
cloudenvy/main.py
cloudenvy/metadata.py
cloudenvy.egg-info/PKG-INFO
cloudenvy.egg-info/SOURCES.txt
cloudenvy.egg-info/dependency_links.txt
cloudenvy.egg-info/entry_points.txt
cloudenvy.egg-info/requires.txt
cloudenvy.egg-info/top_level.txt
cloudenvy/clouds/__init__.py
cloudenvy/clouds/ec2.py
cloudenvy/clouds/openstack.py
cloudenvy/commands/__init__.py
cloudenvy/commands/destroy.py
cloudenvy/commands/dotfiles.py
cloudenvy/commands/files.py
cloudenvy/commands/init.py
cloudenvy/commands/ip.py
cloudenvy/commands/list.py
cloudenvy/commands/provision.py
cloudenvy/commands/run.py
cloudenvy/commands/scp.py
cloudenvy/commands/snapshot.py
cloudenvy/commands/ssh.py
cloudenvy/commands/up.py