Metadata-Version: 1.0
Name: cloudenvy
Version: 0.9.0
Summary: Fast provisioning on openstack clouds.
Home-page: https://github.com/cloudenvy/cloudenvy
Author: Brian Waldon
Author-email: bcwaldon@gmail.com
License: UNKNOWN
Platform: UNKNOWN
